rhppandas/__init__.py
rhppandas/rhppandas.py
rhppandas/util/__init__.py
rhppandas/util/const.py
rhppandas/util/functools.py
rhppandas-0.2.1.dist-info/LICENSE
rhppandas-0.2.1.dist-info/METADATA
rhppandas-0.2.1.dist-info/WHEEL
rhppandas-0.2.1.dist-info/RECORD
