Metadata-Version: 2.3
Name: rhppandas
Version: 0.2.1
Summary: Integration of rHEALPixDGGS and Pandas/GeoPandas
License: GPL-3.0-or-later
Keywords: python,rHEALPix,rhealpixdggs,geospatial,geopandas,pandas,integration
Author: MWLR
Author-email: lawr@landcareresearch.co.nz
Requires-Python: >=3.11
Classifier: Development Status :: 2 - Pre-Alpha
Classifier: Programming Language :: Python :: 3
Classifier: Topic :: Scientific/Engineering :: GIS
Provides-Extra: dev
Requires-Dist: geopandas
Requires-Dist: numpy
Requires-Dist: numpy
Requires-Dist: pandas
Requires-Dist: pytest ; extra == "dev"
Requires-Dist: pytest-cov ; extra == "dev"
Requires-Dist: rhealpixdggs
Requires-Dist: shapely
Requires-Dist: typing-extensions
Project-URL: bug_reports, https://github.com/manaakiwhenua/rHP-Pandas/issues
Project-URL: source, https://github.com/manaakiwhenua/rHP-Pandas
